drawing3d/helpers.py
drawing3d/constants.py
drawing3d/build_ffi.py
drawing3d/_drawing3d.abi3.so
drawing3d/version.py
drawing3d/window.py
drawing3d/simple3d.py
drawing3d/drawlist.py
drawing3d/__init__.py
drawing3d/eventlist.py
drawing3d/camera.py
drawing3d-0.1.2.dist-info/LICENSE
drawing3d-0.1.2.dist-info/METADATA
drawing3d-0.1.2.dist-info/RECORD
drawing3d-0.1.2.dist-info/top_level.txt
drawing3d-0.1.2.dist-info/WHEEL
