Metadata-Version: 2.1
Name: drawing3d
Version: 0.1.2
Summary: A drawing 3D library for easy visualization
Author: Tolga Demirdal
Project-URL: Homepage, https://github.com/shadymeowy/python-drawing3d
License-File: LICENSE
Requires-Dist: cffi >=1.0.0
Requires-Dist: numpy >=1.0.0
